pysensorpush/__init__.py
pysensorpush/const.py
pysensorpush/sensor.py
pysensorpush-0.1.8.dist-info/LICENSE.md
pysensorpush-0.1.8.dist-info/METADATA
pysensorpush-0.1.8.dist-info/WHEEL
pysensorpush-0.1.8.dist-info/top_level.txt
pysensorpush-0.1.8.dist-info/zip-safe
pysensorpush-0.1.8.dist-info/RECORD
